oneNeuron/__init__.py
oneNeuron/perceptron.py
oneNeuron/utils.py
oneNeuron_pypi_amolbarwal-0.0.21.dist-info/LICENSE
oneNeuron_pypi_amolbarwal-0.0.21.dist-info/METADATA
oneNeuron_pypi_amolbarwal-0.0.21.dist-info/WHEEL
oneNeuron_pypi_amolbarwal-0.0.21.dist-info/top_level.txt
oneNeuron_pypi_amolbarwal-0.0.21.dist-info/RECORD
